pyfof.cpython-37m-x86_64-linux-gnu.so
pyfof-0.1.5.dist-info/WHEEL
pyfof-0.1.5.dist-info/METADATA
pyfof-0.1.5.dist-info/top_level.txt
pyfof-0.1.5.dist-info/RECORD
