Metadata-Version: 2.1
Name: pyfof
Version: 0.1.5
Summary: Friends-of-friends cluster finding in python
Home-page: https://github.com/simongibbons/pyfof
Author: Simon Gibbons
Author-email: simongibbons@gmail.com
License: MIT
Keywords: clustering,friends-of-friends
Platform: UNKNOWN
Requires-Dist: numpy
